youqu3_boom/__init__.py
youqu3_boom/__version__.py
youqu3_boom/cli.py
youqu3_boom-2024.6.13.dist-info/METADATA
youqu3_boom-2024.6.13.dist-info/WHEEL
youqu3_boom-2024.6.13.dist-info/entry_points.txt
youqu3_boom-2024.6.13.dist-info/licenses/LICENSE
youqu3_boom-2024.6.13.dist-info/RECORD
